caos_reborn-2.0.1.data/scripts/caos
caoslib/__init__.py
caoslib/defined/__init__.py
caoslib/defined/constants.py
caoslib/defined/generator.py
caoslib/defined/post_init.py
caoslib/initialization/__init__.py
caoslib/initialization/init.py
caoslib/offline/__init__.py
caoslib/offline/generate.py
caoslib/offline/help.py
caoslib/offline/modify.py
caoslib/offline/test.py
caoslib/saving_tests/__init__.py
caoslib/src/__init__.py
caoslib/src/auth.py
caoslib/src/standings.py
caoslib/src/style.py
caoslib/src/summary.py
caoslib/src/sync.py
caoslib/src/validator.py
caoslib/utils/__init__.py
caos_reborn-2.0.1.dist-info/METADATA
caos_reborn-2.0.1.dist-info/WHEEL
caos_reborn-2.0.1.dist-info/top_level.txt
caos_reborn-2.0.1.dist-info/RECORD
