Metadata-Version: 2.1
Name: caos-reborn
Version: 2.0.1
Summary: Multifunctional tool for caos course
Home-page: https://github.com/Melnikovartem/caos-reborn
Author: Artem Melnikov & Alex Koryakov
Author-email: melnikovam10@gmail.com
License: UNKNOWN
Platform: UNKNOWN
Requires-Dist: clint
Requires-Dist: beautifulsoup4
Requires-Dist: requests
